asynction/__init__.py
asynction/__main__.py
asynction/cli.py
asynction/docs.py
asynction/exceptions.py
asynction/mock_server.py
asynction/py.typed
asynction/security.py
asynction/server.py
asynction/types.py
asynction/utils.py
asynction/validation.py
asynction/templates/__init__.py
asynction/templates/index.html.j2
asynction-0.8.3.dist-info/LICENSE.md
asynction-0.8.3.dist-info/METADATA
asynction-0.8.3.dist-info/WHEEL
asynction-0.8.3.dist-info/entry_points.txt
asynction-0.8.3.dist-info/top_level.txt
asynction-0.8.3.dist-info/zip-safe
asynction-0.8.3.dist-info/RECORD
