Metadata-Version: 2.1
Name: asynction
Version: 0.8.3
Summary: SocketIO framework driven by the AsyncAPI specification. Built on top of Flask-SocketIO. Inspired by Connexion.
Home-page: https://github.com/dedoussis/asynction
Author: Dimitrios Dedoussis
Author-email: dimitrios@dedouss.is
License: MIT
Keywords: asyncapi websockets socketio socket.io api oauth flask microservice framework specification flask-socketio connexion mock documentation docs playground
Platform: UNKNOWN
Classifier: Development Status :: 4 - Beta
Classifier: Intended Audience :: Developers
Classifier: Operating System :: OS Independent
Classifier: Topic :: Internet :: WWW/HTTP :: WSGI :: Application
Classifier: Topic :: Software Development :: Libraries :: Application Frameworks
Classifier: Framework :: Flask
Classifier: License :: OSI Approved :: MIT License
Classifier: Natural Language :: English
Classifier: Programming Language :: Python :: 3
Classifier: Programming Language :: Python :: 3.7
Classifier: Programming Language :: Python :: 3.8
Classifier: Programming Language :: Python :: 3.9
Classifier: Programming Language :: Python :: 3.10
Requires-Python: >=3.7
License-File: LICENSE.md
Requires-Dist: Flask-SocketIO (<6.0.0,>=5.0.0)
Requires-Dist: Flask (<3.0.0,>=0.9.0)
Requires-Dist: jsonschema (<5.0.0,>=4.0.0)
Requires-Dist: PyYAML (<7.0.0,>=5.3.0)
Requires-Dist: svarog (<2.0.0,>=0.1.6)
Requires-Dist: typing-extensions (<5.0.0,>=3.7.2)
Provides-Extra: cli
Requires-Dist: Faker (<14.0.0,>=11.0.0) ; extra == 'cli'
Requires-Dist: hypothesis-jsonschema (==0.22.0) ; extra == 'cli'
Requires-Dist: importlib-metadata (<5.0.0,>=4.8.0) ; extra == 'cli'
Requires-Dist: simple-websocket (<1.0.0,>=0.5.0) ; extra == 'cli'
Provides-Extra: mock
Requires-Dist: Faker (<14.0.0,>=11.0.0) ; extra == 'mock'
Requires-Dist: hypothesis-jsonschema (==0.22.0) ; extra == 'mock'
